sterces_cli/__init__.py
sterces_cli/cli.py
sterces_cli/constants.py
sterces_cli/entries/__init__.py
sterces_cli/entries/commands.py
sterces_cli/foos.py
sterces_cli/groups/__init__.py
sterces_cli/groups/commands.py
sterces_cli/py.typed
sterces_cli-0.1.0.dist-info/LICENSE
sterces_cli-0.1.0.dist-info/METADATA
sterces_cli-0.1.0.dist-info/WHEEL
sterces_cli-0.1.0.dist-info/entry_points.txt
sterces_cli-0.1.0.dist-info/RECORD
