Metadata-Version: 2.3
Name: sterces-cli
Version: 0.1.0
Summary: Command line interface for pykeepass
License: MIT
Author: Quien Sabe
Author-email: qs5579@mail.com
Requires-Python: >=3.10,<4.0
Classifier: Development Status :: 4 - Beta
Classifier: Environment :: Console
Classifier: Intended Audience :: End Users/Desktop
Classifier: Intended Audience :: System Administrators
Classifier: License :: OSI Approved :: MIT License
Classifier: Operating System :: POSIX :: Linux
Classifier: Programming Language :: Python :: 3
Classifier: Programming Language :: Python :: 3.10
Classifier: Programming Language :: Python :: 3.11
Classifier: Programming Language :: Python :: 3.12
Classifier: Programming Language :: Python :: 3.13
Classifier: Programming Language :: Python :: 3 :: Only
Classifier: Topic :: Utilities
Classifier: Typing :: Typed
Requires-Dist: click (>=8.1.0,<9.0.0)
Requires-Dist: dateparser (>=1.2.1,<2.0.0)
Requires-Dist: loguru (>=0.7.3,<0.8.0)
Requires-Dist: sterces (>=0.1.1,<0.2.0)
Project-URL: Documentation, https://python-sterces.readthedocs.io/en/stable
Project-URL: Homepage, https://github.com/wtfo-guru/sterces
